README.md
setup.cfg
setup.py
resolver/__init__.py
resolver/secretsmanager.py
sceptre_secretsmanager_resolver.egg-info/PKG-INFO
sceptre_secretsmanager_resolver.egg-info/SOURCES.txt
sceptre_secretsmanager_resolver.egg-info/dependency_links.txt
sceptre_secretsmanager_resolver.egg-info/entry_points.txt
sceptre_secretsmanager_resolver.egg-info/not-zip-safe
sceptre_secretsmanager_resolver.egg-info/requires.txt
sceptre_secretsmanager_resolver.egg-info/top_level.txt