Metadata-Version: 2.1
Name: sceptre-secretsmanager-resolver
Version: 0.0.1
Summary: UNKNOWN
Home-page: https://github.com/haseebr/sceptre-secretsmanager-resolver
Author: Sceptre
Author-email: me@haseeb.co
License: Apache2
Keywords: sceptre,sceptre-resolver
Platform: UNKNOWN
Classifier: Intended Audience :: Developers
Classifier: Natural Language :: English
Classifier: Environment :: Console
Classifier: Programming Language :: Python :: 2.7
Classifier: Programming Language :: Python :: 3.5
Classifier: Programming Language :: Python :: 3.6
Classifier: Programming Language :: Python :: 3.7
Provides-Extra: test
